san/__init__.py
san/api_config.py
san/async_batch.py
san/available_metrics.py
san/batch.py
san/env_vars.py
san/error.py
san/execute_sql.py
san/get.py
san/get_many.py
san/graphql.py
san/metadata.py
san/metric_complexity.py
san/pandas_utils.py
san/query.py
san/query_constants.py
san/sanbase_graphql.py
san/sanbase_graphql_helper.py
san/transform.py
san/utility.py
san/extras/__init__.py
san/extras/backtest.py
san/extras/event_study.py
san/extras/triple_barrier.py
san/extras/utils.py
san/extras/strategy/__init__.py
san/extras/strategy/assets.py
san/extras/strategy/prices.py
san/extras/strategy/sanx.py
san/extras/strategy/signals.py
san/extras/strategy/strategy.py
san/tests/__init__.py
san/tests/conftest.py
san/tests/test_batch.py
san/tests/test_get.py
san/tests/test_sanbase_integration.py
san/tests/utils.py
sanpy-0.12.4.dist-info/licenses/LICENSE.md
sanpy-0.12.4.dist-info/METADATA
sanpy-0.12.4.dist-info/WHEEL
sanpy-0.12.4.dist-info/top_level.txt
sanpy-0.12.4.dist-info/RECORD
