Metadata-Version: 2.4
Name: sanpy
Version: 0.12.4
Summary: Package for Santiment API access with python
Home-page: https://github.com/santiment/sanpy
Author: Santiment
Author-email: admin@santiment.net
License: MIT
License-File: LICENSE.md
Requires-Dist: pandas>=1.3.0
Requires-Dist: requests
Requires-Dist: iso8601
Requires-Dist: setuptools
Provides-Extra: extras
Requires-Dist: numpy; extra == "extras"
Requires-Dist: matplotlib; extra == "extras"
Requires-Dist: scipy; extra == "extras"
Requires-Dist: mlfinlab; extra == "extras"
Provides-Extra: dev
Requires-Dist: ruff; extra == "dev"
Requires-Dist: pytest; extra == "dev"
Dynamic: author
Dynamic: author-email
Dynamic: description
Dynamic: description-content-type
Dynamic: home-page
Dynamic: license
Dynamic: license-file
Dynamic: provides-extra
Dynamic: requires-dist
Dynamic: summary
